{
  "gitSyncId": "685e483118280a5cf36d2a8a_8bb4dbe1-3ab4-4cc1-b506-6fb5eb0ed817",
  "id": "Reporting_JSObject1.myFun1",
  "pluginId": "js-plugin",
  "pluginType": "JS",
  "unpublishedAction": {
    "actionConfiguration": {
      "encodeParamsToggle": true,
      "jsArguments": [],
      "paginationType": "NONE",
      "timeoutInMillisecond": 10000
    },
    "clientSideExecution": true,
    "collectionId": "Reporting_JSObject1",
    "confirmBeforeExecute": false,
    "datasource": {
      "isAutoGenerated": false,
      "name": "UNUSED_DATASOURCE",
      "pluginId": "js-plugin"
    },
    "dynamicBindingPathList": [
      {
        "key": "body"
      }
    ],
    "fullyQualifiedName": "JSObject1.myFun1",
    "name": "myFun1",
    "pageId": "Reporting",
    "runBehaviour": "MANUAL",
    "userSetOnLoad": false
  }
}